audisto_exporter
