Metadata-Version: 1.0
Name: audisto-exporter
Version: 1.0.1
Summary: UNKNOWN
Home-page: https://github.com/ZeitOnline/audisto_exporter
Author: Wolfgang Schnerring
Author-email: wolfgang.schnerring@zeit.de
License: BSD
Platform: UNKNOWN
